[{"i":"cities_68006","n":"18 de Marzo"},{"i":"cities_68027","n":"Acajete"},{"i":"cities_68042","n":"Acateno"},{"i":"cities_68044","n":"Acatepec"},{"i":"cities_68049","n":"Acatlán"},{"i":"cities_68051","n":"Acatlán de Osorio"},{"i":"cities_68053","n":"Acatzingo"},{"i":"cities_68056","n":"Acaxtlahuacán de Albino Zertuche"},{"i":"cities_68069","n":"Acteopan"},{"i":"cities_68070","n":"Actipan"},{"i":"cities_68071","n":"Actipan de Morelos"},{"i":"cities_68074","n":"Acuaco"},{"i":"cities_68076","n":"Acuexcomac"},{"i":"cities_68137","n":"Ahuacatlán"},{"i":"cities_68143","n":"Ahuatempan"},{"i":"cities_68145","n":"Ahuatepec"},{"i":"cities_68147","n":"Ahuatepec de Camino"},{"i":"cities_68149","n":"Ahuatlán"},{"i":"cities_68150","n":"Ahuaxintitla"},{"i":"cities_68151","n":"Ahuazotepec"},{"i":"cities_68153","n":"Ahuehuetitla"},{"i":"cities_68164","n":"Ajalpan"},{"i":"cities_76393","n":"Álamos Tepetitlán"},{"i":"cities_68176","n":"Albino Zertuche"},{"i":"cities_68201","n":"Alhuaca"},{"i":"cities_68204","n":"Aljojuca"},{"i":"cities_68206","n":"Allende"},{"i":"cities_68210","n":"Almecatla"},{"i":"cities_68213","n":"Almolonga"},{"i":"cities_68226","n":"Altepexi"},{"i":"cities_76398","n":"Álvaro Obregón"},{"i":"cities_68242","n":"Amatitlán de Azueta"},{"i":"cities_68254","n":"Ameluca"},{"i":"cities_68256","n":"Amixtlán"},{"i":"cities_68257","n":"Amozoc"},{"i":"cities_68258","n":"Amozoc de Mota"},{"i":"cities_68268","n":"Analco de Ponciano Arriaga (Santa Cruz Analco)"},{"i":"cities_68290","n":"Apango de Zaragoza"},{"i":"cities_68292","n":"Apantéopan"},{"i":"cities_68293","n":"Apapantilla"},{"i":"cities_68298","n":"Apatauyan"},{"i":"cities_68327","n":"Aquixtla"},{"i":"cities_68377","n":"Artículo Primero Constitucional"},{"i":"cities_68389","n":"Atalpan"},{"i":"cities_68394","n":"Atecax"},{"i":"cities_68396","n":"Atempan"},{"i":"cities_68398","n":"Atencingo"},{"i":"cities_68402","n":"Atexcal"},{"i":"cities_68408","n":"Atla"},{"i":"cities_68420","n":"Atlequizayan"},{"i":"cities_68422","n":"Atlixco"},{"i":"cities_68426","n":"Atoluca"},{"i":"cities_68435","n":"Atoyatempan"},{"i":"cities_68438","n":"Atzala"},{"i":"cities_68440","n":"Atzalán"},{"i":"cities_68441","n":"Atzingo (La Cumbre)"},{"i":"cities_68442","n":"Atzitzintla"},{"i":"cities_68455","n":"Axutla"},{"i":"cities_68456","n":"Axuxco"},{"i":"cities_68464","n":"Ayotla"},{"i":"cities_68465","n":"Ayotoxco de Guerrero"},{"i":"cities_68470","n":"Ayutla"},{"i":"cities_68476","n":"Azumbilla"},{"i":"cities_68546","n":"Barrio de Nuevo León"},{"i":"cities_68581","n":"Bellavista de Victoria (San José Bellavista)"},{"i":"cities_68592","n":"Benito Juárez"},{"i":"cities_68608","n":"Beristain"},{"i":"cities_68615","n":"Bienvenido"},{"i":"cities_68662","n":"Buena Vista"},{"i":"cities_68674","n":"Buenavista"},{"i":"cities_68683","n":"Buenavista de Juárez"},{"i":"cities_68677","n":"Buenavista Tetela"},{"i":"cities_68690","n":"Buenos Aires"},{"i":"cities_68712","n":"Cacaloxúchitl"},{"i":"cities_68724","n":"Cala Norte"},{"i":"cities_68725","n":"Cala Sur"},{"i":"cities_68739","n":"Calipan"},{"i":"cities_68743","n":"Calmeca"},{"i":"cities_68746","n":"Calpanería Atezquilla"},{"i":"cities_68765","n":"Camocuautla"},{"i":"cities_68766","n":"Camotepec"},{"i":"cities_68791","n":"Candelaria Portezuelo"},{"i":"cities_68828","n":"Carmen Serdán"},{"i":"cities_68846","n":"Casa Blanca"},{"i":"cities_68868","n":"Caxhuacán"},{"i":"cities_68958","n":"Chalchihuapan"},{"i":"cities_68986","n":"Chapulco"},{"i":"cities_69014","n":"Chiautla de Tapia"},{"i":"cities_69016","n":"Chicahuaxtla"},{"i":"cities_69022","n":"Chichicapa"},{"i":"cities_69025","n":"Chichicuautla"},{"i":"cities_69032","n":"Chichiquila"},{"i":"cities_69042","n":"Chiconcuautla"},{"i":"cities_69045","n":"Chicontla"},{"i":"cities_69052","n":"Chietla"},{"i":"cities_69053","n":"Chigmecatitlán"},{"i":"cities_69054","n":"Chignahuapan"},{"i":"cities_69059","n":"Chila"},{"i":"cities_69060","n":"Chila de Juárez"},{"i":"cities_69061","n":"Chila de la Sal"},{"i":"cities_69068","n":"Chilchotla"},{"i":"cities_69084","n":"Chinantla"},{"i":"cities_69085","n":"Chinautla"},{"i":"cities_69088","n":"Chipahuatlán"},{"i":"cities_69089","n":"Chipilo de Francisco Javier Mina"},{"i":"cities_69103","n":"Cholula"},{"i":"cities_69135","n":"Cinco de Mayo"},{"i":"cities_69187","n":"Ciudad de Chiautla de Tapia"},{"i":"cities_69188","n":"Ciudad de Cuetzalan"},{"i":"cities_69192","n":"Ciudad de Tlatlauquitepec"},{"i":"cities_69181","n":"Ciudad Serdán"},{"i":"cities_69217","n":"Coahuixco"},{"i":"cities_69226","n":"Coatepec"},{"i":"cities_69232","n":"Coatzingo"},{"i":"cities_69252","n":"Cohuecán"},{"i":"cities_69276","n":"Colonia Agrícola de Ocotepec (Colonia San José)"},{"i":"cities_69344","n":"Colonia Obrera"},{"i":"cities_69413","n":"Colucan"},{"i":"cities_69420","n":"Comaltepec"},{"i":"cities_69433","n":"Concepción Capulac (La Ex-Hacienda)"},{"i":"cities_69436","n":"Concepción Cuautla"},{"i":"cities_69473","n":"Copila"},{"i":"cities_69480","n":"Coronango"},{"i":"cities_69481","n":"Coronel Tito Hernández"},{"i":"cities_69511","n":"Coxcatlán"},{"i":"cities_69512","n":"Coxolico"},{"i":"cities_69519","n":"Coyomeapan"},{"i":"cities_69522","n":"Coyotepec"},{"i":"cities_69549","n":"Cuacnopalan"},{"i":"cities_69550","n":"Cuacuila"},{"i":"cities_69559","n":"Cuanalá"},{"i":"cities_69562","n":"Cuapiaxtla de Madero"},{"i":"cities_69569","n":"Cuatro Caminos"},{"i":"cities_69573","n":"Cuauhtamazaco"},{"i":"cities_69584","n":"Cuauhtémoc"},{"i":"cities_69586","n":"Cuautempan"},{"i":"cities_69589","n":"Cuautinchán"},{"i":"cities_69593","n":"Cuautlancingo"},{"i":"cities_69595","n":"Cuautotola"},{"i":"cities_69596","n":"Cuautotolapan (San José)"},{"i":"cities_69598","n":"Cuaxoxpan"},{"i":"cities_69599","n":"Cuaxuxpa"},{"i":"cities_69600","n":"Cuayuca de Andrade"},{"i":"cities_69618","n":"Cuesta Blanca"},{"i":"cities_69622","n":"Cuetzalan"},{"i":"cities_69623","n":"Cuetzalan del Progreso"},{"i":"cities_69624","n":"Cuexpala"},{"i":"cities_69652","n":"Cuyoaco"},{"i":"cities_69705","n":"Dolores Hidalgo"},{"i":"cities_69708","n":"Domingo Arenas"},{"i":"cities_69862","n":"El Capulo (La Quebradora)"},{"i":"cities_69874","n":"El Carmen"},{"i":"cities_69897","n":"El Chacal"},{"i":"cities_69953","n":"El Encanto del Cerril"},{"i":"cities_69973","n":"El Fuerte de la Unión"},{"i":"cities_70041","n":"El Mirador"},{"i":"cities_70047","n":"El Molino"},{"i":"cities_70080","n":"El Palmar"},{"i":"cities_70132","n":"El Progreso"},{"i":"cities_70162","n":"El Rincón Citlaltépetl"},{"i":"cities_70251","n":"El Veladero"},{"i":"cities_70273","n":"Eloxochitlán"},{"i":"cities_70275","n":"Emancipación Quetzalapa"},{"i":"cities_70295","n":"Emilio Carranza (Santa Cruz)"},{"i":"cities_70296","n":"Emilio Portes Gil"},{"i":"cities_70327","n":"Esperanza"},{"i":"cities_70466","n":"Francisco I. Madero"},{"i":"cities_70471","n":"Francisco Ignacio Madero"},{"i":"cities_70476","n":"Francisco Sarabia"},{"i":"cities_70482","n":"Francisco Villa"},{"i":"cities_70483","n":"Francisco Z. Mena"},{"i":"cities_70506","n":"Galaxia la Calera"},{"i":"cities_70531","n":"General Felipe Ángeles"},{"i":"cities_70548","n":"Gilberto Camacho"},{"i":"cities_70647","n":"Gómez Poniente"},{"i":"cities_70556","n":"González Ortega"},{"i":"cities_70559","n":"Grajales"},{"i":"cities_70576","n":"Guadalupe"},{"i":"cities_70579","n":"Guadalupe Calderón"},{"i":"cities_70581","n":"Guadalupe Enríquez"},{"i":"cities_70586","n":"Guadalupe Libertad"},{"i":"cities_70588","n":"Guadalupe Morelos"},{"i":"cities_70589","n":"Guadalupe Santa Ana"},{"i":"cities_70590","n":"Guadalupe Sarabia"},{"i":"cities_70598","n":"Guadalupe Victoria"},{"i":"cities_70607","n":"Guadalupe Zaragoza"},{"i":"cities_70668","n":"Hermenegildo Galeana"},{"i":"cities_70706","n":"Honey"},{"i":"cities_70715","n":"Huachinantla"},{"i":"cities_70717","n":"Huahuaxtla"},{"i":"cities_70722","n":"Huajoyuca"},{"i":"cities_70738","n":"Huaquechula"},{"i":"cities_70742","n":"Huatlatlauca"},{"i":"cities_70744","n":"Huauchinango"},{"i":"cities_70747","n":"Huautla de Jiménez"},{"i":"cities_70748","n":"Huaxcaleca"},{"i":"cities_70758","n":"Huehuetla"},{"i":"cities_70759","n":"Huehuetlan el Chico"},{"i":"cities_70760","n":"Huehuetlán el Grande"},{"i":"cities_70764","n":"Huejonapan"},{"i":"cities_70766","n":"Huejotzingo"},{"i":"cities_70775","n":"Hueyapan"},{"i":"cities_70780","n":"Hueyotlipan"},{"i":"cities_70783","n":"Hueytamalco"},{"i":"cities_70785","n":"Hueytlalpan"},{"i":"cities_70790","n":"Huilacapixtla"},{"i":"cities_70807","n":"Huitzilac"},{"i":"cities_70808","n":"Huitzilan"},{"i":"cities_70811","n":"Huitziltepec"},{"i":"cities_70813","n":"Huitzmaloc"},{"i":"cities_70816","n":"Huixcolotla"},{"i":"cities_70834","n":"Icxotitla"},{"i":"cities_70839","n":"Ignacio Allende (Concepción)"},{"i":"cities_70843","n":"Ignacio Manuel Altamirano"},{"i":"cities_70856","n":"Ignacio Zaragoza"},{"i":"cities_70896","n":"Itzoteno"},{"i":"cities_70898","n":"Ixcamilpa de Guerrero"},{"i":"cities_70901","n":"Ixcaquixtla"},{"i":"cities_70921","n":"Ixtacamaxtitlán"},{"i":"cities_70925","n":"Ixtahuiata (La Legua)"},{"i":"cities_70935","n":"Ixtepec"},{"i":"cities_70936","n":"Ixticpan"},{"i":"cities_70938","n":"Ixtlahuaca"},{"i":"cities_70939","n":"Ixtlahuaca Barrio"},{"i":"cities_70947","n":"Ixtolco de Morelos"},{"i":"cities_70953","n":"Izúcar de Matamoros"},{"i":"cities_70980","n":"Jalpan"},{"i":"cities_70991","n":"Jaltocan"},{"i":"cities_71034","n":"Jesús Nazareno"},{"i":"cities_71043","n":"Jicolapa"},{"i":"cities_71047","n":"Jilotzingo"},{"i":"cities_71070","n":"Jolalpan"},{"i":"cities_71080","n":"Jonotla"},{"i":"cities_71082","n":"Jopala"},{"i":"cities_71099","n":"José María Morelos"},{"i":"cities_71115","n":"Juan C. Bonilla"},{"i":"cities_71128","n":"Juan de la Granja"},{"i":"cities_71119","n":"Juan Galindo"},{"i":"cities_71125","n":"Juan N. Méndez"},{"i":"cities_71147","n":"Juárez Coronaco"},{"i":"cities_71205","n":"La Cañada"},{"i":"cities_71223","n":"La Compañia"},{"i":"cities_71298","n":"La Galarza"},{"i":"cities_71301","n":"La Gloria"},{"i":"cities_71346","n":"La Laguna"},{"i":"cities_71357","n":"La Libertad"},{"i":"cities_71380","n":"La Magdalena"},{"i":"cities_71384","n":"La Magdalena Tetela Morelos"},{"i":"cities_71386","n":"La Magdalena Yancuitlalpan"},{"i":"cities_71416","n":"La Pahua"},{"i":"cities_71469","n":"La Purísima"},{"i":"cities_71476","n":"La Resurrección"},{"i":"cities_71493","n":"La Soledad"},{"i":"cities_71512","n":"La Trinidad Chautenco"},{"i":"cities_71515","n":"La Trinidad Tianguismanalco"},{"i":"cities_71520","n":"La Unión"},{"i":"cities_71524","n":"La Unión Ejido Mexcaltepec"},{"i":"cities_71541","n":"Lacapan Camallagne"},{"i":"cities_71545","n":"Lafragua"},{"i":"cities_71589","n":"Las Colonias de Hidalgo"},{"i":"cities_71607","n":"Las Lajas"},{"i":"cities_71611","n":"Las Lomas"},{"i":"cities_71626","n":"Las Nieves"},{"i":"cities_71894","n":"Lázaro Cárdenas"},{"i":"cities_71658","n":"Leacaman"},{"i":"cities_71672","n":"Libertad Álvaro Obregón"},{"i":"cities_71674","n":"Libres"},{"i":"cities_71682","n":"Lipuntahuaca"},{"i":"cities_71709","n":"Loma Alta"},{"i":"cities_71717","n":"Loma Bonita"},{"i":"cities_71747","n":"Lomas de Romero"},{"i":"cities_71754","n":"Lomas de Santa Cruz"},{"i":"cities_71872","n":"Los Ángeles Tetela"},{"i":"cities_71794","n":"Los Cristales (Talican)"},{"i":"cities_71800","n":"Los Encinos"},{"i":"cities_71803","n":"Los Garcías"},{"i":"cities_71851","n":"Los Reyes de Juárez"},{"i":"cities_71850","n":"Los Reyes Tlanechicolpan"},{"i":"cities_71924","n":"Magdalena Cuayucatepec"},{"i":"cities_71953","n":"Manantiales"},{"i":"cities_71960","n":"Manuel Edgardo Ávalos (San Isidro)"},{"i":"cities_72021","n":"Matlahuacales Aquiles Serdán"},{"i":"cities_72022","n":"Matzaco"},{"i":"cities_72259","n":"Máximo Serdán"},{"i":"cities_72040","n":"Mazapiltepec"},{"i":"cities_72042","n":"Mazatepec"},{"i":"cities_72053","n":"Mecapalapa"},{"i":"cities_72093","n":"Metlaltoyuca"},{"i":"cities_72098","n":"Mexcalcuautla"},{"i":"cities_72115","n":"Miahuatlán"},{"i":"cities_72118","n":"Michac"},{"i":"cities_72129","n":"Miguel Hidalgo"},{"i":"cities_72134","n":"Miguel Negrete"},{"i":"cities_72156","n":"Miravalles"},{"i":"cities_72168","n":"Mixtla"},{"i":"cities_72232","n":"Morelos"},{"i":"cities_72234","n":"Morelos Cañada"},{"i":"cities_72249","n":"Moyotzingo"},{"i":"cities_72274","n":"Nanacatlán"},{"i":"cities_72291","n":"Naupan"},{"i":"cities_72293","n":"Nauzontla"},{"i":"cities_72302","n":"Nealtican"},{"i":"cities_72303","n":"Necaxa"},{"i":"cities_72304","n":"Necoxcalco"},{"i":"cities_72305","n":"Necoxtla"},{"i":"cities_72310","n":"Nenehuaca"},{"i":"cities_72315","n":"Nexpan"},{"i":"cities_72316","n":"Nexticapan"},{"i":"cities_72325","n":"Nicolás Bravo"},{"i":"cities_72349","n":"Nopalucan"},{"i":"cities_72397","n":"Nuevo México"},{"i":"cities_72400","n":"Nuevo Necaxa"},{"i":"cities_72453","n":"Ocotepec"},{"i":"cities_72457","n":"Ocotlamanic"},{"i":"cities_72459","n":"Ocotlán de Betancourt"},{"i":"cities_72461","n":"Ocotlán de Venustiano Carranza"},{"i":"cities_72502","n":"Olintla"},{"i":"cities_72505","n":"Ometepec"},{"i":"cities_72519","n":"Oriental"},{"i":"cities_72556","n":"Oyameles de Hidalgo"},{"i":"cities_72557","n":"Ozelonacaxtla"},{"i":"cities_72576","n":"Pahuatlán de Valle"},{"i":"cities_72591","n":"Palmar de Bravo"},{"i":"cities_72593","n":"Palmarito Tochapan"},{"i":"cities_72627","n":"Pantepec"},{"i":"cities_72632","n":"Papaloctipan"},{"i":"cities_72638","n":"Papatlazolco"},{"i":"cities_72679","n":"Paso Carretas"},{"i":"cities_72682","n":"Paso Nacional"},{"i":"cities_72707","n":"Patla"},{"i":"cities_72735","n":"Pericotepec"},{"i":"cities_72745","n":"Petlalcingo"},{"i":"cities_72747","n":"Pezmatlán"},{"i":"cities_72756","n":"Piaxtla"},{"i":"cities_72834","n":"Pochálcatl"},{"i":"cities_72903","n":"Primero de Mayo"},{"i":"cities_72912","n":"Progreso"},{"i":"cities_72919","n":"Progreso de Juárez"},{"i":"cities_72925","n":"Puebla"},{"i":"cities_73003","n":"Putlunichuchut (Vista Hermosa)"},{"i":"cities_73015","n":"Quamila"},{"i":"cities_73017","n":"Quecholac"},{"i":"cities_73018","n":"Quechulac"},{"i":"cities_73044","n":"Rafael J. García"},{"i":"cities_73059","n":"Rancho Chico"},{"i":"cities_73066","n":"Rancho Nuevo"},{"i":"cities_73107","n":"Ricardo Flores Magón"},{"i":"cities_73136","n":"Rincón de los Reyes"},{"i":"cities_73223","n":"Saltillo"},{"i":"cities_73236","n":"San Acateno"},{"i":"cities_73242","n":"San Agustín Atzompa"},{"i":"cities_73249","n":"San Agustín Huixaxtla"},{"i":"cities_73254","n":"San Agustín Tlaxco"},{"i":"cities_73267","n":"San Andrés"},{"i":"cities_73270","n":"San Andrés Azumiatla"},{"i":"cities_73271","n":"San Andrés Cacaloapan"},{"i":"cities_73272","n":"San Andrés Calpan"},{"i":"cities_73274","n":"San Andrés Cholula"},{"i":"cities_73283","n":"San Andrés Hueyacatitla"},{"i":"cities_73291","n":"San Andrés Payuca"},{"i":"cities_73301","n":"San Andrés Yahuitlalpan"},{"i":"cities_73318","n":"San Antonio"},{"i":"cities_73320","n":"San Antonio Alpanocan"},{"i":"cities_73322","n":"San Antonio Atotonilco"},{"i":"cities_73328","n":"San Antonio Cañada"},{"i":"cities_73337","n":"San Antonio Juárez"},{"i":"cities_73390","n":"San Antonio la Portilla"},{"i":"cities_73338","n":"San Antonio Matlahuacales"},{"i":"cities_73339","n":"San Antonio Mihuacán"},{"i":"cities_73342","n":"San Antonio Ocopetlatlán"},{"i":"cities_73344","n":"San Antonio Portezuelo"},{"i":"cities_73348","n":"San Antonio Soledad"},{"i":"cities_73351","n":"San Antonio Tecolco"},{"i":"cities_73356","n":"San Antonio Tlacamilco"},{"i":"cities_73358","n":"San Antonio Tlatenco"},{"i":"cities_73360","n":"San Antonio Virreyes"},{"i":"cities_73393","n":"San Baltazar Atlimeyaya"},{"i":"cities_73417","n":"San Bartolomé"},{"i":"cities_73424","n":"San Bartolomé Hueyapan"},{"i":"cities_73432","n":"San Bernabé Temoxtitla"},{"i":"cities_73435","n":"San Bernardino Lagunas"},{"i":"cities_73436","n":"San Bernardino Tlaxcalancingo"},{"i":"cities_73449","n":"San Buenaventura"},{"i":"cities_73454","n":"San Buenaventura Tecaltzingo"},{"i":"cities_73457","n":"San Carlos"},{"i":"cities_73478","n":"San Cristóbal Hidalgo"},{"i":"cities_73484","n":"San Cristóbal los Nava"},{"i":"cities_73482","n":"San Cristóbal Xochimilpa"},{"i":"cities_73490","n":"San Diego"},{"i":"cities_73498","n":"San Diego el Organal"},{"i":"cities_73500","n":"San Diego la Mesa Tochimiltzingo"},{"i":"cities_73516","n":"San Felipe Hidalgo"},{"i":"cities_73519","n":"San Felipe Otlaltepec"},{"i":"cities_73622","n":"San Félix Hidalgo"},{"i":"cities_73623","n":"San Félix Rijo"},{"i":"cities_73544","n":"San Francisco"},{"i":"cities_73559","n":"San Francisco Cuapa"},{"i":"cities_73560","n":"San Francisco Cuautlancingo"},{"i":"cities_73566","n":"San Francisco Independencia (Santa María Aserradero)"},{"i":"cities_73582","n":"San Francisco Ocotlán"},{"i":"cities_73598","n":"San Francisco Tepeyecac"},{"i":"cities_73603","n":"San Francisco Tláloc"},{"i":"cities_73607","n":"San Francisco Zacapexpan"},{"i":"cities_73627","n":"San Gabriel Chilac"},{"i":"cities_73630","n":"San Gabriel Tetzoyocán"},{"i":"cities_73642","n":"San Gregorio Atzompa"},{"i":"cities_73643","n":"San Gregorio Aztotoacan"},{"i":"cities_73645","n":"San Hipólito"},{"i":"cities_73670","n":"San Isidro"},{"i":"cities_73679","n":"San Isidro Huilotepec"},{"i":"cities_73682","n":"San Isidro Monterrosas"},{"i":"cities_73684","n":"San Isidro Vista Hermosa"},{"i":"cities_73702","n":"San Jerónimo Almoloya"},{"i":"cities_73704","n":"San Jerónimo Axochitlán"},{"i":"cities_73707","n":"San Jerónimo Coaltepec"},{"i":"cities_73709","n":"San Jerónimo Coyula"},{"i":"cities_73712","n":"San Jerónimo Ocotitla"},{"i":"cities_73721","n":"San Jerónimo Xayacatlán"},{"i":"cities_73739","n":"San José"},{"i":"cities_73740","n":"San José Acateno"},{"i":"cities_73741","n":"San José Alchichica"},{"i":"cities_73749","n":"San José Buena Vista"},{"i":"cities_73750","n":"San José Buenavista"},{"i":"cities_73753","n":"San José Carpinteros"},{"i":"cities_73757","n":"San José Chiapa"},{"i":"cities_73763","n":"San José Cuyachapa"},{"i":"cities_73815","n":"San José de Gracia"},{"i":"cities_73770","n":"San José Ixtapa"},{"i":"cities_73773","n":"San José Manzanitos"},{"i":"cities_73775","n":"San José Monte Chiquito"},{"i":"cities_73778","n":"San José Ozumba"},{"i":"cities_73793","n":"San José Tilapa"},{"i":"cities_73795","n":"San José Tlacuitlapan"},{"i":"cities_73864","n":"San Juan Amecac"},{"i":"cities_73865","n":"San Juan Atenco"},{"i":"cities_73868","n":"San Juan Atzingo"},{"i":"cities_73869","n":"San Juan Atzompa"},{"i":"cities_73882","n":"San Juan Colón"},{"i":"cities_73886","n":"San Juan Cuauhtémoc"},{"i":"cities_73887","n":"San Juan Cuautla"},{"i":"cities_73891","n":"San Juan Epatlán"},{"i":"cities_73897","n":"San Juan Huiluco"},{"i":"cities_73899","n":"San Juan Ixcaquixtla"},{"i":"cities_73915","n":"San Juan Pancoac"},{"i":"cities_73921","n":"San Juan Raboso"},{"i":"cities_73927","n":"San Juan Tahitic"},{"i":"cities_73930","n":"San Juan Tejaluca"},{"i":"cities_73931","n":"San Juan Tejupa"},{"i":"cities_73935","n":"San Juan Tepulco"},{"i":"cities_73936","n":"San Juan Tetla"},{"i":"cities_73938","n":"San Juan Tezongo"},{"i":"cities_73946","n":"San Juan Tuxco"},{"i":"cities_73949","n":"San Juan Xiutetelco"},{"i":"cities_73993","n":"San Lorenzo"},{"i":"cities_74000","n":"San Lorenzo Chiautzingo"},{"i":"cities_74005","n":"San Lorenzo Joya de Rodríguez"},{"i":"cities_74016","n":"San Lorenzo Tlaxipehuala"},{"i":"cities_74026","n":"San Lucas Atzala"},{"i":"cities_74040","n":"San Lucas el Grande"},{"i":"cities_74041","n":"San Lucas el Viejo"},{"i":"cities_74044","n":"San Luis Ajajalpan"},{"i":"cities_74050","n":"San Luis Coyotzingo"},{"i":"cities_74056","n":"San Luis Tehuiloyocan"},{"i":"cities_74070","n":"San Marcos Eloxochitlán"},{"i":"cities_74075","n":"San Marcos Tlacoyalco"},{"i":"cities_74087","n":"San Martín"},{"i":"cities_74091","n":"San Martín Caltenco"},{"i":"cities_74096","n":"San Martín Esperilla"},{"i":"cities_74100","n":"San Martín Mazateopan"},{"i":"cities_74102","n":"San Martín Ojo de Agua"},{"i":"cities_74106","n":"San Martín Texmelucan"},{"i":"cities_74083","n":"San Martin Texmelucan de Labastida"},{"i":"cities_74108","n":"San Martín Tlamapa"},{"i":"cities_74109","n":"San Martín Tlapala"},{"i":"cities_74120","n":"San Mateo Ayecac"},{"i":"cities_74123","n":"San Mateo Capultitlán"},{"i":"cities_74132","n":"San Mateo Ozolco"},{"i":"cities_74133","n":"San Mateo Parra"},{"i":"cities_74136","n":"San Mateo Soltepec"},{"i":"cities_74145","n":"San Matías Atzala"},{"i":"cities_74144","n":"San Matias Tlalancaleca"},{"i":"cities_74156","n":"San Miguel Aguacomulican"},{"i":"cities_74163","n":"San Miguel Analco"},{"i":"cities_74166","n":"San Miguel Atlapulco"},{"i":"cities_74169","n":"San Miguel Canoa"},{"i":"cities_74235","n":"San Miguel del Milagro"},{"i":"cities_74236","n":"San Miguel del Progreso"},{"i":"cities_74179","n":"San Miguel Espejo"},{"i":"cities_74182","n":"San Miguel Ixitlán"},{"i":"cities_74190","n":"San Miguel Ocotenco"},{"i":"cities_74194","n":"San Miguel Papaxtla"},{"i":"cities_74202","n":"San Miguel Tecuitlapa"},{"i":"cities_74204","n":"San Miguel Tenango"},{"i":"cities_74205","n":"San Miguel Tenextatiloyan"},{"i":"cities_74208","n":"San Miguel Tianguistenco"},{"i":"cities_74209","n":"San Miguel Tianguizolco"},{"i":"cities_74223","n":"San Miguel Xoxtla"},{"i":"cities_74226","n":"San Miguel Zoapan"},{"i":"cities_74227","n":"San Miguel Zozutla"},{"i":"cities_74245","n":"San Nicolas Buenos Aires"},{"i":"cities_74274","n":"San Nicolás de los Ranchos"},{"i":"cities_74267","n":"San Nicolás Tolentino"},{"i":"cities_74268","n":"San Nicolás Zecalacoayan"},{"i":"cities_74269","n":"San Nicolás Zoyapetlayoca"},{"i":"cities_74278","n":"San Pablito"},{"i":"cities_74280","n":"San Pablo Ahuatempa"},{"i":"cities_74281","n":"San Pablo Anicano"},{"i":"cities_74305","n":"San Pablo de las Tunas"},{"i":"cities_74317","n":"San Pedro Atmatla"},{"i":"cities_74320","n":"San Pedro Benito Juárez"},{"i":"cities_74327","n":"San Pedro Cholula"},{"i":"cities_74331","n":"San Pedro Cuayuca"},{"i":"cities_74343","n":"San Pedro Itztla"},{"i":"cities_74416","n":"San Pedro la Joya"},{"i":"cities_74353","n":"San Pedro Matamoros"},{"i":"cities_74366","n":"San Pedro Petlacotla"},{"i":"cities_74377","n":"San Pedro Temamatla"},{"i":"cities_74381","n":"San Pedro Tetitlán"},{"i":"cities_74388","n":"San Pedro Tlaolantongo"},{"i":"cities_74399","n":"San Pedro Yancuitlalpan"},{"i":"cities_74400","n":"San Pedro Yeloixtlahuaca"},{"i":"cities_74402","n":"San Pedro Zacachimalpa"},{"i":"cities_74431","n":"San Rafael Ixtapalucan"},{"i":"cities_74436","n":"San Rafael Tlanalapan"},{"i":"cities_74445","n":"San Salvador (Naranjillo)"},{"i":"cities_74448","n":"San Salvador El Seco"},{"i":"cities_74451","n":"San Salvador el Verde"},{"i":"cities_74453","n":"San Sebastián"},{"i":"cities_74459","n":"San Sebastián Alcomunga"},{"i":"cities_74476","n":"San Sebastián de Aparicio"},{"i":"cities_74470","n":"San Sebastián Teteles"},{"i":"cities_74471","n":"San Sebastián Tlacotepec"},{"i":"cities_74473","n":"San Sebastián Villanueva"},{"i":"cities_74483","n":"San Simón"},{"i":"cities_74485","n":"San Simón Atzitzintla"},{"i":"cities_74496","n":"San Vicente Boquerón"},{"i":"cities_74499","n":"San Vicente Coyotepec"},{"i":"cities_74516","n":"Sanctorum"},{"i":"cities_74525","n":"Santa Ana Acozautla"},{"i":"cities_74532","n":"Santa Ana Coapan"},{"i":"cities_74533","n":"Santa Ana Coatepec"},{"i":"cities_74541","n":"Santa Ana Necoxtla"},{"i":"cities_74549","n":"Santa Ana Xalmimilulco"},{"i":"cities_74590","n":"Santa Catarina Tlaltempan"},{"i":"cities_74591","n":"Santa Catarina Villanueva"},{"i":"cities_74596","n":"Santa Cecilia Tepetitlán"},{"i":"cities_74597","n":"Santa Clara"},{"i":"cities_74601","n":"Santa Clara Huitziltepec"},{"i":"cities_74613","n":"Santa Cruz Acapa"},{"i":"cities_74615","n":"Santa Cruz Ajajalpan"},{"i":"cities_74622","n":"Santa Cruz Cuautomatitla"},{"i":"cities_74651","n":"Santa Cruz el Porvenir"},{"i":"cities_74625","n":"Santa Cruz Huitziltepec"},{"i":"cities_74632","n":"Santa Cruz Otlatla"},{"i":"cities_74642","n":"Santa Cruz Texmalaquilla"},{"i":"cities_74643","n":"Santa Cruz Xaltetela"},{"i":"cities_74667","n":"Santa Inés Tecuexcomac"},{"i":"cities_74668","n":"Santa Inés Varela la Luz"},{"i":"cities_74677","n":"Santa Isabel Cholula"},{"i":"cities_74687","n":"Santa Lucía Cosamaloapan"},{"i":"cities_74717","n":"Santa María Atexcac"},{"i":"cities_74695","n":"Santa Maria Coatepec"},{"i":"cities_74812","n":"Santa María del Monte"},{"i":"cities_74736","n":"Santa María Guadalupe Tecola"},{"i":"cities_74747","n":"Santa María Ixtiyucán"},{"i":"cities_74820","n":"Santa María la Alta"},{"i":"cities_74758","n":"Santa María Malacatepec"},{"i":"cities_74765","n":"Santa María Nenetzintla"},{"i":"cities_74766","n":"Santa María Nepopualco"},{"i":"cities_74777","n":"Santa María Techachalco"},{"i":"cities_74784","n":"Santa María Texmelucan"},{"i":"cities_74794","n":"Santa María Xonacatepec"},{"i":"cities_74800","n":"Santa María Zacatepec"},{"i":"cities_74701","n":"Santa Martha Hidalgo"},{"i":"cities_74831","n":"Santa Rita"},{"i":"cities_74833","n":"Santa Rita Tlahuapan"},{"i":"cities_74836","n":"Santa Rosa"},{"i":"cities_74870","n":"Santiago"},{"i":"cities_74871","n":"Santiago Acatlán"},{"i":"cities_74873","n":"Santiago Acozac"},{"i":"cities_74875","n":"Santiago Alseseca"},{"i":"cities_74880","n":"Santiago Atzitzihuacán"},{"i":"cities_74894","n":"Santiago Coltzingo"},{"i":"cities_74926","n":"Santiago Momoxpan"},{"i":"cities_74943","n":"Santiago Tenango"},{"i":"cities_74973","n":"Santiago Yancuictlalpan"},{"i":"cities_74998","n":"Santo Domingo Atoyatempan"},{"i":"cities_75001","n":"Santo Domingo Huehuetlán"},{"i":"cities_75021","n":"Santo Nombre"},{"i":"cities_75026","n":"Santo Tomás Chautla"},{"i":"cities_75052","n":"Sección 23"},{"i":"cities_75113","n":"Soledad Morelos"},{"i":"cities_75120","n":"Soltepec"},{"i":"cities_75124","n":"Sosa"},{"i":"cities_75159","n":"Tacopan"},{"i":"cities_75200","n":"Tanamacoyan"},{"i":"cities_75212","n":"Tanhuixco"},{"i":"cities_75241","n":"Tatauzoquico"},{"i":"cities_75242","n":"Tatoxcac"},{"i":"cities_75254","n":"Teacalco de Dorantes (San José Teacalco)"},{"i":"cities_75260","n":"Tecali"},{"i":"cities_75263","n":"Tecamachalco"},{"i":"cities_75277","n":"Tecoltepec"},{"i":"cities_75281","n":"Tecomatlán"},{"i":"cities_75287","n":"Tecpantzacoalco"},{"i":"cities_75291","n":"Tecuanipa"},{"i":"cities_75292","n":"Tecuanipan"},{"i":"cities_75296","n":"Tehuacán"},{"i":"cities_75300","n":"Tehuitzingo"},{"i":"cities_75304","n":"Tejaluca"},{"i":"cities_75321","n":"Teloxtoc"},{"i":"cities_75322","n":"Telpatlán"},{"i":"cities_75325","n":"Temalacayuca"},{"i":"cities_75335","n":"Temextla"},{"i":"cities_75347","n":"Tenampulco"},{"i":"cities_75356","n":"Tenango de las Flores"},{"i":"cities_75379","n":"Teontepec"},{"i":"cities_75380","n":"Teopantlán"},{"i":"cities_75386","n":"Teotlalco"},{"i":"cities_75387","n":"Teotlaltzingo"},{"i":"cities_75395","n":"Tepanco"},{"i":"cities_75396","n":"Tepango"},{"i":"cities_75397","n":"Tepango de Rodríguez"},{"i":"cities_75398","n":"Tepapayeca"},{"i":"cities_75401","n":"Tepatlaxco de Hidalgo"},{"i":"cities_75402","n":"Tepazolco"},{"i":"cities_75403","n":"Tepeaca"},{"i":"cities_75413","n":"Tepeojuma"},{"i":"cities_75416","n":"Tepeteno de Iturbide"},{"i":"cities_75422","n":"Tepetitán Reyeshogpan de Hidalgo"},{"i":"cities_75424","n":"Tepetlacolco"},{"i":"cities_75433","n":"Tepetzingo"},{"i":"cities_75436","n":"Tepetzintla"},{"i":"cities_75437","n":"Tepetzitzintla"},{"i":"cities_75438","n":"Tepexco"},{"i":"cities_75439","n":"Tepexi de Rodríguez"},{"i":"cities_75442","n":"Tepeyahualco"},{"i":"cities_75443","n":"Tepeyahualco de Cuauhtémoc"},{"i":"cities_75445","n":"Tepeyehualco de Hidalgo"},{"i":"cities_75478","n":"Tetela de Ocampo"},{"i":"cities_75480","n":"Tetelcingo"},{"i":"cities_75482","n":"Teteles de Avila Castillo"},{"i":"cities_75503","n":"Texcala"},{"i":"cities_75504","n":"Texcalapa de Juárez"},{"i":"cities_75521","n":"Texocoyohuac"},{"i":"cities_75524","n":"Tezhuatepec"},{"i":"cities_75525","n":"Teziutlan"},{"i":"cities_75528","n":"Tezonteopan de Bonilla"},{"i":"cities_75535","n":"Tianguismanalco"},{"i":"cities_75553","n":"Tierra Negra"},{"i":"cities_75566","n":"Tilapa"},{"i":"cities_75597","n":"Tlacamilco"},{"i":"cities_75602","n":"Tlachichuca"},{"i":"cities_75615","n":"Tlacotepec"},{"i":"cities_75618","n":"Tlacotepec (San Mateo)"},{"i":"cities_75619","n":"Tlacotepec de Benito Juárez"},{"i":"cities_75620","n":"Tlacotepec de José Manzo"},{"i":"cities_75625","n":"Tlacuilotepec"},{"i":"cities_75629","n":"Tlahuapan"},{"i":"cities_75634","n":"Tlaixpan"},{"i":"cities_75653","n":"Tlaltenango"},{"i":"cities_75656","n":"Tlaltepango"},{"i":"cities_75662","n":"Tlamanca"},{"i":"cities_75663","n":"Tlamanca de Hernández"},{"i":"cities_75665","n":"Tlamaya Grande"},{"i":"cities_75669","n":"Tlanalapan"},{"i":"cities_75671","n":"Tlancualpican"},{"i":"cities_75672","n":"Tlanepantla"},{"i":"cities_75674","n":"Tlaola"},{"i":"cities_75676","n":"Tlapacoya"},{"i":"cities_75680","n":"Tlapanalá"},{"i":"cities_75684","n":"Tlatempa"},{"i":"cities_75688","n":"Tlatlauquitepec"},{"i":"cities_75694","n":"Tlaxcalantongo"},{"i":"cities_75697","n":"Tlaxco"},{"i":"cities_75699","n":"Tlaxco (Santiago Tlaxco)"},{"i":"cities_75704","n":"Tlaxpanaloya"},{"i":"cities_75706","n":"Tlayehualancingo"},{"i":"cities_75710","n":"Tlixco"},{"i":"cities_75713","n":"Tochimilco"},{"i":"cities_75714","n":"Tochtepec"},{"i":"cities_75725","n":"Tomaquilapa"},{"i":"cities_75726","n":"Tomatlán"},{"i":"cities_75736","n":"Tonalixco"},{"i":"cities_75754","n":"Totoltepec"},{"i":"cities_75755","n":"Totoltepec de Guerrero"},{"i":"cities_75761","n":"Toxtla"},{"i":"cities_75762","n":"Tozihuic"},{"i":"cities_75785","n":"Tronconal"},{"i":"cities_75789","n":"Tula"},{"i":"cities_75796","n":"Tulcingo"},{"i":"cities_75797","n":"Tulcingo de Valle"},{"i":"cities_75799","n":"Tulimanca"},{"i":"cities_75826","n":"Tuxtla"},{"i":"cities_75828","n":"Tuzamapan"},{"i":"cities_75832","n":"Tuzuapan"},{"i":"cities_75837","n":"Tzicatlacoyan"},{"i":"cities_75839","n":"Tzicatlán"},{"i":"cities_75841","n":"Tzinacapan"},{"i":"cities_75869","n":"Unidad Grajales INFONAVIT"},{"i":"cities_75953","n":"Venta Grande"},{"i":"cities_75958","n":"Venustiano Carranza"},{"i":"cities_75979","n":"Vicente Guerrero"},{"i":"cities_75992","n":"Villa Avila Camacho"},{"i":"cities_75998","n":"Villa Cuauhtémoc"},{"i":"cities_76034","n":"Villa Mariano Matamoros"},{"i":"cities_76110","n":"Xacaxomulco"},{"i":"cities_76112","n":"Xalacapan de Lucke"},{"i":"cities_76118","n":"Xalitzintla"},{"i":"cities_76122","n":"Xaltepec"},{"i":"cities_76123","n":"Xaltepuxtla"},{"i":"cities_76125","n":"Xalticpac"},{"i":"cities_76129","n":"Xayacatlán de Bravo"},{"i":"cities_76139","n":"Xicotepec"},{"i":"cities_76140","n":"Xicotepec de Juárez"},{"i":"cities_76141","n":"Xicotlán"},{"i":"cities_76145","n":"Xilocuautla"},{"i":"cities_76146","n":"Xiloxochico de Rafael Ávila Camacho"},{"i":"cities_76149","n":"Xitlama"},{"i":"cities_76150","n":"Xiutetelco"},{"i":"cities_76156","n":"Xochiapulco"},{"i":"cities_76161","n":"Xochicuautla"},{"i":"cities_76164","n":"Xochiltepec"},{"i":"cities_76168","n":"Xochimilco"},{"i":"cities_76169","n":"Xochinanacatlán"},{"i":"cities_76173","n":"Xochitepec"},{"i":"cities_76180","n":"Xochitlán de Vicente Suárez"},{"i":"cities_76175","n":"Xochitlan Todos Santos"},{"i":"cities_76176","n":"Xochitlaxco (San Baltazar)"},{"i":"cities_76184","n":"Xocotepéc"},{"i":"cities_76190","n":"Xoloateno"},{"i":"cities_76192","n":"Xolotla"},{"i":"cities_76196","n":"Xonalpu"},{"i":"cities_76197","n":"Xonocuautla"},{"i":"cities_76203","n":"Xoxonacatla"},{"i":"cities_76205","n":"Xuchapa"},{"i":"cities_76216","n":"Yaonahuac"},{"i":"cities_76231","n":"Yehualtepec"},{"i":"cities_76243","n":"Yopi"},{"i":"cities_76261","n":"Zacaola"},{"i":"cities_76262","n":"Zacapala"},{"i":"cities_76264","n":"Zacapechpan"},{"i":"cities_76265","n":"Zacapoaxtla"},{"i":"cities_76275","n":"Zacatepec"},{"i":"cities_76277","n":"Zacatlán"},{"i":"cities_76291","n":"Zahuatlán de Morelos (San José)"},{"i":"cities_76307","n":"Zapotitlán"},{"i":"cities_76315","n":"Zaragoza"},{"i":"cities_76325","n":"Zautla"},{"i":"cities_76327","n":"Zempoala"},{"i":"cities_76334","n":"Zihuateutla"},{"i":"cities_76341","n":"Zinacatepec"},{"i":"cities_76355","n":"Zoatecpan"},{"i":"cities_76359","n":"Zolonquiapa"},{"i":"cities_76363","n":"Zongozotla"},{"i":"cities_76368","n":"Zoquiapan"},{"i":"cities_76369","n":"Zoquiopan"},{"i":"cities_76373","n":"Zoquitlán"},{"i":"cities_76377","n":"Zoyatitla"},{"i":"cities_76380","n":"Zoyotla"},{"i":"cities_76381","n":"Zozocolco de Guerrero"}]