[{"i":"cities_76793","n":"Bama"},{"i":"cities_76801","n":"Benisheikh"},{"i":"cities_76808","n":"Biu"},{"i":"cities_76814","n":"Bornu Yassu"},{"i":"cities_76825","n":"Damasak"},{"i":"cities_76827","n":"Damboa"},{"i":"cities_76842","n":"Dikwa"},{"i":"cities_76874","n":"Gamboru"},{"i":"cities_76901","n":"Gwoza"},{"i":"cities_76991","n":"Kukawa"},{"i":"cities_77016","n":"Magumeri"},{"i":"cities_77018","n":"Maiduguri"},{"i":"cities_77024","n":"Marte"},{"i":"cities_77030","n":"Miringa"},{"i":"cities_77033","n":"Monguno"},{"i":"cities_77040","n":"Ngala"},{"i":"cities_77101","n":"Shaffa"},{"i":"cities_77103","n":"Shani"},{"i":"cities_77113","n":"Tokombere"},{"i":"cities_77117","n":"Uba"},{"i":"cities_77138","n":"Wuyo"},{"i":"cities_77139","n":"Yajiwa"}]