[{"i":"cities_62290","n":"Aberdeen"},{"i":"cities_62293","n":"Accompong"},{"i":"cities_62303","n":"Alligator Pond"},{"i":"cities_62326","n":"Balaclava"},{"i":"cities_62328","n":"Ballards  Valley"},{"i":"cities_62333","n":"Barbary Hall"},{"i":"cities_62360","n":"Bigwoods"},{"i":"cities_62363","n":"Black River"},{"i":"cities_62371","n":"Bogue"},{"i":"cities_62381","n":"Braes River"},{"i":"cities_62390","n":"Brighton"},{"i":"cities_62393","n":"Brompton"},{"i":"cities_62401","n":"Bull Savanna"},{"i":"cities_62402","n":"Bull Savannah"},{"i":"cities_62405","n":"Burnt Savannah"},{"i":"cities_62419","n":"Carisbrook"},{"i":"cities_62483","n":"Cotterwood"},{"i":"cities_62487","n":"Crawford"},{"i":"cities_62534","n":"Elderslie"},{"i":"cities_62577","n":"Fullerswood"},{"i":"cities_62584","n":"Giddy Hall"},{"i":"cities_62586","n":"Ginger Hill"},{"i":"cities_62599","n":"Goshen"},{"i":"cities_62651","n":"Holland"},{"i":"cities_62655","n":"Hopeton"},{"i":"cities_62682","n":"Junction"},{"i":"cities_62699","n":"Lacovia"},{"i":"cities_62705","n":"Leeds"},{"i":"cities_62717","n":"Lititz"},{"i":"cities_62739","n":"Maggotty"},{"i":"cities_62743","n":"Malvern"},{"i":"cities_62770","n":"Merrywood"},{"i":"cities_62771","n":"Middle Quarters"},{"i":"cities_62805","n":"Mountainside"},{"i":"cities_62806","n":"Mulgrave"},{"i":"cities_62807","n":"Myersville"},{"i":"cities_62809","n":"Nain"},{"i":"cities_62818","n":"New Market"},{"i":"cities_62823","n":"Newell"},{"i":"cities_62826","n":"Newton"},{"i":"cities_62854","n":"Parottee"},{"i":"cities_62872","n":"Pedro Plains"},{"i":"cities_62877","n":"Pepper"},{"i":"cities_62884","n":"Pisgah"},{"i":"cities_62889","n":"Pondside"},{"i":"cities_62902","n":"Potsdam"},{"i":"cities_62909","n":"Quick Step"},{"i":"cities_62915","n":"Red Bank"},{"i":"cities_62923","n":"Retirement"},{"i":"cities_62951","n":"Rose Hall"},{"i":"cities_62960","n":"Russels"},{"i":"cities_62971","n":"Santa Cruz"},{"i":"cities_62976","n":"Scholefield"},{"i":"cities_62993","n":"Siloah"},{"i":"cities_62996","n":"Slipe"},{"i":"cities_63004","n":"Southfield"},{"i":"cities_63017","n":"Springfield"},{"i":"cities_63049","n":"Thornton"},{"i":"cities_63054","n":"Top Hill"},{"i":"cities_63062","n":"Treasure Beach"},{"i":"cities_63083","n":"Warminister"},{"i":"cities_63086","n":"Watchwell"},{"i":"cities_63100","n":"White Hill"}]