[{"i":"cities_68019","n":"Abelardo L. Rodríguez"},{"i":"cities_68197","n":"Alfredo V. Bonfil"},{"i":"cities_68223","n":"Altamira de Zináparo"},{"i":"cities_68393","n":"Atasta"},{"i":"cities_68481","n":"Bacabchén"},{"i":"cities_68696","n":"Bécal"},{"i":"cities_68606","n":"Benito Juárez Uno"},{"i":"cities_68630","n":"Bolonchén de Rejón"},{"i":"cities_68726","n":"Calakmul"},{"i":"cities_68741","n":"Calkiní"},{"i":"cities_68770","n":"Campeche"},{"i":"cities_68789","n":"Candelaria"},{"i":"cities_68827","n":"Carmen"},{"i":"cities_68838","n":"Carrillo Puerto"},{"i":"cities_68858","n":"Castamay"},{"i":"cities_68968","n":"Champotón"},{"i":"cities_69019","n":"Chicbul"},{"i":"cities_69087","n":"Chiná"},{"i":"cities_69117","n":"Chunchintok"},{"i":"cities_69195","n":"Ciudad del Carmen"},{"i":"cities_69294","n":"Colonia Emiliano Zapata"},{"i":"cities_69463","n":"Constitución"},{"i":"cities_69636","n":"Cumpich"},{"i":"cities_69689","n":"División del Norte"},{"i":"cities_69712","n":"Don Samuel"},{"i":"cities_69735","n":"Dzibalchén"},{"i":"cities_69741","n":"Dzitbalché"},{"i":"cities_69824","n":"El Aguacatal"},{"i":"cities_70058","n":"El Naranjo"},{"i":"cities_70324","n":"Escárcega"},{"i":"cities_70662","n":"Hampolol"},{"i":"cities_70663","n":"Haro"},{"i":"cities_70664","n":"Hecelchakán"},{"i":"cities_70707","n":"Hool"},{"i":"cities_70708","n":"Hopelchén"},{"i":"cities_70883","n":"Isla Aguada"},{"i":"cities_70892","n":"Iturbide"},{"i":"cities_71331","n":"La Joya"},{"i":"cities_71354","n":"La Libertad"},{"i":"cities_71663","n":"Lerma"},{"i":"cities_71677","n":"Licenciado Gustavo Díaz Ordaz (18 de Marzo)"},{"i":"cities_71808","n":"Los Laureles"},{"i":"cities_71951","n":"Mamantel"},{"i":"cities_72016","n":"Matamoros"},{"i":"cities_72030","n":"Maya Tecún I"},{"i":"cities_72405","n":"Nuevo Progreso"},{"i":"cities_72426","n":"Nunkiní"},{"i":"cities_72584","n":"Palizada"},{"i":"cities_72759","n":"Pich"},{"i":"cities_72830","n":"Pocboc"},{"i":"cities_72847","n":"Pomuch"},{"i":"cities_73190","n":"Sabancuy"},{"i":"cities_73331","n":"San Antonio Cárdenas"},{"i":"cities_73347","n":"San Antonio Sahcabchén"},{"i":"cities_73573","n":"San Francisco Kobén"},{"i":"cities_74299","n":"San Pablo Pixtún"},{"i":"cities_74608","n":"Santa Cruz"},{"i":"cities_74624","n":"Santa Cruz Ex-Hacienda"},{"i":"cities_74636","n":"Santa Cruz Pueblo"},{"i":"cities_75003","n":"Santo Domingo Kesté"},{"i":"cities_75065","n":"Seybaplaya"},{"i":"cities_75076","n":"Sihochac"},{"i":"cities_75137","n":"Suc-Tuc"},{"i":"cities_75215","n":"Tankuché"},{"i":"cities_75345","n":"Tenabo"},{"i":"cities_75390","n":"Tepakán"},{"i":"cities_75563","n":"Tikinmul"},{"i":"cities_75865","n":"Ukúm"},{"i":"cities_76029","n":"Villa Madero"},{"i":"cities_76130","n":"Xbacab"},{"i":"cities_76151","n":"Xmabén"},{"i":"cities_76204","n":"Xpujil"},{"i":"cities_76358","n":"Zoh-Laguna"}]