[{"i":"cities_57599","n":"Agar"},{"i":"cities_57611","n":"Ajaigarh"},{"i":"cities_57626","n":"Akodia"},{"i":"cities_57631","n":"Alampur"},{"i":"cities_57639","n":"Alirajpur"},{"i":"cities_57646","n":"Alot"},{"i":"cities_57691","n":"Amanganj"},{"i":"cities_57659","n":"Amarkantak"},{"i":"cities_57663","n":"Amarpatan"},{"i":"cities_57664","n":"Amarwara"},{"i":"cities_57673","n":"Ambah"},{"i":"cities_57680","n":"Amla"},{"i":"cities_57706","n":"Anjad"},{"i":"cities_57719","n":"Antri"},{"i":"cities_57721","n":"Anuppur"},{"i":"cities_134462","n":"Aron"},{"i":"cities_57750","n":"Ashoknagar"},{"i":"cities_57752","n":"Ashta"},{"i":"cities_58103","n":"Babai"},{"i":"cities_57788","n":"Badarwas"},{"i":"cities_57793","n":"Badnawar"},{"i":"cities_58106","n":"Bag"},{"i":"cities_58111","n":"Bagli"},{"i":"cities_57811","n":"Baihar"},{"i":"cities_57813","n":"Baikunthpur"},{"i":"cities_57821","n":"Bakshwaho"},{"i":"cities_58119","n":"Balaghat"},{"i":"cities_57824","n":"Baldeogarh"},{"i":"cities_57838","n":"Bamna"},{"i":"cities_58122","n":"Bamor Kalan"},{"i":"cities_57839","n":"Bamora"},{"i":"cities_57842","n":"Banda"},{"i":"cities_57868","n":"Barela"},{"i":"cities_57870","n":"Barghat"},{"i":"cities_57871","n":"Bargi"},{"i":"cities_57872","n":"Barhi"},{"i":"cities_57888","n":"Barwani"},{"i":"cities_58148","n":"Basoda"},{"i":"cities_57913","n":"Begamganj"},{"i":"cities_57935","n":"Beohari"},{"i":"cities_57936","n":"Berasia"},{"i":"cities_57940","n":"Betma"},{"i":"cities_57942","n":"Betul"},{"i":"cities_57943","n":"Betul Bazar"},{"i":"cities_58006","n":"Bhabhra"},{"i":"cities_57959","n":"Bhainsdehi"},{"i":"cities_58011","n":"Bhander"},{"i":"cities_58012","n":"Bhanpura"},{"i":"cities_57975","n":"Bhawaniganj"},{"i":"cities_57980","n":"Bhikangaon"},{"i":"cities_57982","n":"Bhind"},{"i":"cities_57985","n":"Bhitarwar"},{"i":"cities_57995","n":"Bhopal"},{"i":"cities_58025","n":"Biaora"},{"i":"cities_58038","n":"Bijawar"},{"i":"cities_58036","n":"Bijrauni"},{"i":"cities_58073","n":"Bodri"},{"i":"cities_58096","n":"Burhanpur"},{"i":"cities_58097","n":"Burhar"},{"i":"cities_58188","n":"Chanderi"},{"i":"cities_58189","n":"Chandia"},{"i":"cities_58191","n":"Chandla"},{"i":"cities_131532","n":"Chhatarpur"},{"i":"cities_131534","n":"Chhindwara"},{"i":"cities_131543","n":"Chichli"},{"i":"cities_131581","n":"Chorhat"},{"i":"cities_131636","n":"Daboh"},{"i":"cities_131637","n":"Dabra"},{"i":"cities_131651","n":"Damoh"},{"i":"cities_131662","n":"Datia"},{"i":"cities_131691","n":"Deori Khas"},{"i":"cities_131693","n":"Depalpur"},{"i":"cities_131707","n":"Dewas"},{"i":"cities_131749","n":"Dhamnod"},{"i":"cities_131751","n":"Dhana"},{"i":"cities_131753","n":"Dhar"},{"i":"cities_131720","n":"Dharampuri"},{"i":"cities_131775","n":"Dindori"},{"i":"cities_131848","n":"Etawa"},{"i":"cities_132043","n":"Gadarwara"},{"i":"cities_131917","n":"Garha Brahman"},{"i":"cities_131924","n":"Garhakota"},{"i":"cities_131930","n":"Gautampura"},{"i":"cities_131936","n":"Ghansor"},{"i":"cities_131965","n":"Gogapur"},{"i":"cities_131966","n":"Gohadi"},{"i":"cities_132002","n":"Govindgarh"},{"i":"cities_132024","n":"Guna"},{"i":"cities_132033","n":"Gurh"},{"i":"cities_132040","n":"Gwalior"},{"i":"cities_132070","n":"Harda"},{"i":"cities_132071","n":"Harda Khas"},{"i":"cities_132080","n":"Harpalpur"},{"i":"cities_132081","n":"Harrai"},{"i":"cities_132082","n":"Harsud"},{"i":"cities_132145","n":"Hatod"},{"i":"cities_132088","n":"Hatta"},{"i":"cities_132098","n":"Hindoria"},{"i":"cities_132120","n":"Hoshangabad"},{"i":"cities_132180","n":"Iawar"},{"i":"cities_132152","n":"Ichhawar"},{"i":"cities_132158","n":"Iklehra"},{"i":"cities_132166","n":"Indore"},{"i":"cities_132175","n":"Isagarh"},{"i":"cities_132179","n":"Itarsi"},{"i":"cities_132181","n":"Jabalpur"},{"i":"cities_132204","n":"Jaisinghnagar"},{"i":"cities_132206","n":"Jaithari"},{"i":"cities_132309","n":"Jamai"},{"i":"cities_132241","n":"Jaora"},{"i":"cities_132251","n":"Jatara"},{"i":"cities_132314","n":"Jawad"},{"i":"cities_132275","n":"Jhabua"},{"i":"cities_132316","n":"Jiran"},{"i":"cities_132283","n":"Jobat"},{"i":"cities_132333","n":"Kailaras"},{"i":"cities_132336","n":"Kaimori"},{"i":"cities_132382","n":"Kannod"},{"i":"cities_132397","n":"Kareli"},{"i":"cities_132398","n":"Karera"},{"i":"cities_132407","n":"Karrapur"},{"i":"cities_132419","n":"Kasrawad"},{"i":"cities_132420","n":"Katangi"},{"i":"cities_132424","n":"Katni"},{"i":"cities_132511","n":"Khachrod"},{"i":"cities_132453","n":"Khailar"},{"i":"cities_132457","n":"Khajuraho Group of Monuments"},{"i":"cities_132460","n":"Khamaria"},{"i":"cities_132467","n":"Khandwa"},{"i":"cities_132468","n":"Khandwa district"},{"i":"cities_132476","n":"Khargapur"},{"i":"cities_132474","n":"Khargone"},{"i":"cities_132519","n":"Khategaon"},{"i":"cities_132497","n":"Khilchipur"},{"i":"cities_132498","n":"Khirkiyan"},{"i":"cities_132504","n":"Khujner"},{"i":"cities_132507","n":"Khurai"},{"i":"cities_132561","n":"Kolaras"},{"i":"cities_132585","n":"Korwai"},{"i":"cities_132613","n":"Kotar"},{"i":"cities_132598","n":"Kothi"},{"i":"cities_132603","n":"Kotma"},{"i":"cities_132611","n":"Kotwa"},{"i":"cities_132631","n":"Kukshi"},{"i":"cities_132640","n":"Kumbhraj"},{"i":"cities_132741","n":"Lahar"},{"i":"cities_132746","n":"Lakhnadon"},{"i":"cities_132763","n":"Leteri"},{"i":"cities_132766","n":"Lodhikheda"},{"i":"cities_133054","n":"Machalpur"},{"i":"cities_132814","n":"Madhogarh"},{"i":"cities_132833","n":"Maheshwar"},{"i":"cities_132835","n":"Mahgawan"},{"i":"cities_132854","n":"Maihar"},{"i":"cities_132860","n":"Majholi"},{"i":"cities_132864","n":"Maksi"},{"i":"cities_132869","n":"Malhargarh"},{"i":"cities_132930","n":"Manasa"},{"i":"cities_132931","n":"Manawar"},{"i":"cities_132894","n":"Mandideep"},{"i":"cities_132895","n":"Mandla"},{"i":"cities_133075","n":"Mandleshwar"},{"i":"cities_132897","n":"Mandsaur"},{"i":"cities_132907","n":"Mangawan"},{"i":"cities_133080","n":"Manpur"},{"i":"cities_132943","n":"Mau"},{"i":"cities_132947","n":"Mauganj"},{"i":"cities_132973","n":"Mihona"},{"i":"cities_132983","n":"Mohgaon"},{"i":"cities_133003","n":"Morar"},{"i":"cities_132994","n":"Morena"},{"i":"cities_133022","n":"Multai"},{"i":"cities_133028","n":"Mundi"},{"i":"cities_133030","n":"Mungaoli"},{"i":"cities_133042","n":"Murwara"},{"i":"cities_133115","n":"Nagda"},{"i":"cities_133259","n":"Nagod"},{"i":"cities_133197","n":"Naigarhi"},{"i":"cities_133124","n":"Nainpur"},{"i":"cities_133138","n":"Namli"},{"i":"cities_133155","n":"Naraini"},{"i":"cities_133276","n":"Narayangarh"},{"i":"cities_133171","n":"Narsimhapur"},{"i":"cities_133172","n":"Narsinghgarh"},{"i":"cities_133174","n":"Narwar"},{"i":"cities_133179","n":"Nasrullahganj"},{"i":"cities_133202","n":"Neemuch"},{"i":"cities_133207","n":"Nepanagar"},{"i":"cities_133304","n":"Orchha"},{"i":"cities_133308","n":"Pachmarhi"},{"i":"cities_133325","n":"Palera"},{"i":"cities_133530","n":"Pali"},{"i":"cities_133354","n":"Panagar"},{"i":"cities_133344","n":"Panara"},{"i":"cities_133348","n":"Pandhana"},{"i":"cities_133538","n":"Pandhurna"},{"i":"cities_133351","n":"Panna"},{"i":"cities_133542","n":"Pansemal"},{"i":"cities_133371","n":"Parasia"},{"i":"cities_133555","n":"Patan"},{"i":"cities_133381","n":"Patharia"},{"i":"cities_133396","n":"Pawai"},{"i":"cities_133430","n":"Petlawad"},{"i":"cities_133454","n":"Piploda"},{"i":"cities_133462","n":"Pithampur"},{"i":"cities_133481","n":"Porsa"},{"i":"cities_133508","n":"Punasa"},{"i":"cities_133660","n":"Raghogarh"},{"i":"cities_133661","n":"Rahatgarh"},{"i":"cities_133591","n":"Raisen"},{"i":"cities_133675","n":"Rajgarh"},{"i":"cities_133680","n":"Rajnagar"},{"i":"cities_133595","n":"Rajpur"},{"i":"cities_133709","n":"Rampura"},{"i":"cities_133717","n":"Ranapur"},{"i":"cities_133615","n":"Ratangarh"},{"i":"cities_133618","n":"Ratlam"},{"i":"cities_133623","n":"Rehli"},{"i":"cities_133624","n":"Rehti"},{"i":"cities_133633","n":"Rewa"},{"i":"cities_133738","n":"Sabalgarh"},{"i":"cities_134061","n":"Sagar"},{"i":"cities_133757","n":"Sailana"},{"i":"cities_133796","n":"Sanawad"},{"i":"cities_134070","n":"Sanchi"},{"i":"cities_134075","n":"Sanwer"},{"i":"cities_134078","n":"Sarangpur"},{"i":"cities_133820","n":"Satna"},{"i":"cities_133824","n":"Satwas"},{"i":"cities_133826","n":"Saugor"},{"i":"cities_133829","n":"Sausar"},{"i":"cities_133835","n":"Sehore"},{"i":"cities_133838","n":"Sendhwa"},{"i":"cities_133840","n":"Seondha"},{"i":"cities_133842","n":"Seoni"},{"i":"cities_133843","n":"Seoni Malwa"},{"i":"cities_133853","n":"Shahdol"},{"i":"cities_133893","n":"Shahgarh"},{"i":"cities_133899","n":"Shahpur"},{"i":"cities_133904","n":"Shahpura"},{"i":"cities_133910","n":"Shajapur"},{"i":"cities_133912","n":"Shamgarh"},{"i":"cities_133861","n":"Sheopur"},{"i":"cities_133880","n":"Shivpuri"},{"i":"cities_133888","n":"Shujalpur"},{"i":"cities_133922","n":"Sidhi"},{"i":"cities_133926","n":"Sihora"},{"i":"cities_133938","n":"Simaria"},{"i":"cities_133947","n":"Singoli"},{"i":"cities_133948","n":"Singrauli"},{"i":"cities_133956","n":"Sirmaur"},{"i":"cities_133959","n":"Sironj"},{"i":"cities_134090","n":"Sitamau"},{"i":"cities_133981","n":"Sohagi"},{"i":"cities_133982","n":"Sohagpur"},{"i":"cities_134039","n":"Sultanpur"},{"i":"cities_134055","n":"Susner"},{"i":"cities_134230","n":"Tal"},{"i":"cities_134102","n":"Talen"},{"i":"cities_134119","n":"Tarana"},{"i":"cities_134124","n":"Tekanpur"},{"i":"cities_134130","n":"Tendukheda"},{"i":"cities_134132","n":"Teonthar"},{"i":"cities_134137","n":"Thandla"},{"i":"cities_134244","n":"Tikamgarh"},{"i":"cities_134177","n":"Tirodi"},{"i":"cities_134251","n":"Udaipura"},{"i":"cities_134263","n":"Ujjain"},{"i":"cities_134266","n":"Ukwa"},{"i":"cities_134270","n":"Umaria"},{"i":"cities_134271","n":"Umaria District"},{"i":"cities_134276","n":"Umri"},{"i":"cities_134282","n":"Unhel"},{"i":"cities_134354","n":"Vidisha"},{"i":"cities_134418","n":"Waraseoni"}]